edkcore/__init__.py
edkcore/factory/__init__.py
edkcore/factory/context_action_factory.py
edkcore/factory/context_data_factory.py
edkcore/factory/xml_loader_factory.py
edkcore/factory/xml/__init__.py
edkcore/factory/xml/assert_xml_loader.py
edkcore/factory/xml/context_property_xml_loader.py
edkcore/factory/xml/meta_xml_loader.py
edkcore/factory/xml/scene_xml_loader.py
edkcore/schema/contextdata.xsd
edkcore/schema/edk-core.xsd
edkcore/schema/meta.xsd
edkcore/support/__init__.py
edkcore/support/action_state.py
edkcore/support/meta_action.py
edkcore/support/publisher.py
edkcore/support/restore_action.py
edkcore/support/utils.py
edkcore/support/xml_meta_action.py
edkcore/support/xml_scene_action.py
edkcore/support/abstract/__init__.py
edkcore/support/abstract/abc_action.py
edkcore/support/abstract/abc_assert_action.py
edkcore/support/abstract/abc_call_back.py
edkcore/support/abstract/abc_context_action.py
edkcore/support/abstract/abc_getter.py
edkcore/support/abstract/abc_persistence.py
edkcore/support/abstract/abc_persistent_device.py
edkcore/support/abstract/abc_properties.py
edkcore/support/abstract/abc_publisher_action.py
edkcore/support/abstract/abc_serialize.py
edkcore/support/abstract/abc_subscriber.py
edkcore/support/abstract/abc_subscriber_action.py
edkcore/support/abstract/abc_xml_loader.py
edkcore/support/callbacks/__init__.py
edkcore/support/callbacks/nothing.py
edkcore/support/context/__init__.py
edkcore/support/context/context_action_data.py
edkcore/support/context/context_content.py
edkcore/support/context/context_data.py
edkcore/support/context/context_persistent.py
edkcore/support/context/data_info.py
edkcore/support/enums/__init__.py
edkcore/support/enums/action_enum.py
edkcore/support/enums/persistent_enum.py
edkcore/support/enums/state_enum.py
edkcore/support/persistents/__init__.py
edkcore/support/persistents/dict_persistent_device.py
edkcore/support/persistents/persistent_device_connector.py
edkcore/support/persistents/persistent_device_info.py
edkcore-1.0.0.1.dist-info/METADATA
edkcore-1.0.0.1.dist-info/WHEEL
edkcore-1.0.0.1.dist-info/top_level.txt
edkcore-1.0.0.1.dist-info/RECORD
